{
  "generated_at": "2026-02-03",
  "windows": {
    "short_days": 14,
    "primary_days": 56,
    "long_days": 112,
    "all_start": "2024-02-05",
    "all_end": "2026-02-02",
    "primary_start": "2025-12-10",
    "primary_end": "2026-02-03"
  },
  "weighting": {
    "mode": "recent_weighted",
    "recent_window_days": 56,
    "note": "Recent 56 days weighted more heavily; historical data retained to avoid false zero baselines."
  },
  "athlete_meta": {
    "sex": "M",
    "weight_kg": 80,
    "has_weight": true,
    "source": "strava_athlete"
  },
  "disciplines": {
    "run": {
      "units": {
        "volume": "km",
        "session_distance": "km",
        "session_duration": "min",
        "long_session": "km"
      },
      "weekly": {
        "sessions_median": 0.8,
        "volume_median": 6.4,
        "volume_iqr": [
          4.03,
          10.92
        ],
        "zero_weeks": 2,
        "volume_cv": 0.71,
        "weeks_tracked": 9,
        "elevation_gain_median": 0,
        "distance_km_median": 0,
        "distance_km_iqr": [
          0,
          0
        ]
      },
      "session": {
        "distance_median": 4.83,
        "duration_median_min": 27.05,
        "sessions_tracked": 15,
        "elevation_gain_median_m": 0
      },
      "long_session": {
        "weekly_max_median": 4.2
      },
      "intensity": {
        "pace": {
          "distance_weighted_sec_per_km": 329.05,
          "median_sec_per_km": 338.22,
          "sample_count": 15
        },
        "heart_rate": {
          "duration_weighted_bpm": 154.2,
          "median_bpm": 152.16,
          "sample_count": 11
        }
      },
      "coverage": {
        "total_activities": 15,
        "pace_or_speed_coverage_fraction": 1,
        "hr_fraction": 0.73
      },
      "confidence": "low",
      "history": {
        "gap_days": 1,
        "recent": {
          "weekly": {
            "sessions_median": 1,
            "volume_median": 8,
            "volume_iqr": [
              5.036,
              12.305800000000001
            ],
            "zero_weeks": 2,
            "volume_cv": 0.71,
            "weeks_tracked": 9,
            "elevation_gain_median": 0,
            "distance_km_median": 0,
            "distance_km_iqr": [
              0,
              0
            ]
          },
          "session": {
            "distance_median": 5.0389,
            "duration_median_min": 28.283333333333335,
            "sessions_tracked": 15,
            "elevation_gain_median_m": 0
          },
          "long_session": {
            "weekly_max_median": 5.2548
          },
          "intensity": {
            "pace": {
              "distance_weighted_sec_per_km": 326.94,
              "median_sec_per_km": 338.36,
              "sample_count": 15
            },
            "heart_rate": {
              "duration_weighted_bpm": 153.6,
              "median_bpm": 151.2,
              "sample_count": 11
            }
          }
        },
        "historical": {
          "weekly": {
            "sessions_median": 0,
            "volume_median": 0,
            "volume_iqr": [
              0,
              5.383800000000001
            ],
            "zero_weeks": 52,
            "volume_cv": 1.512,
            "weeks_tracked": 97,
            "elevation_gain_median": 0,
            "distance_km_median": 0,
            "distance_km_iqr": [
              0,
              0
            ]
          },
          "session": {
            "distance_median": 4.008,
            "duration_median_min": 22.116666666666667,
            "sessions_tracked": 81,
            "elevation_gain_median_m": 0
          },
          "long_session": {
            "weekly_max_median": 0
          },
          "intensity": {
            "pace": {
              "distance_weighted_sec_per_km": 337.51,
              "median_sec_per_km": 337.66,
              "sample_count": 77
            },
            "heart_rate": {
              "duration_weighted_bpm": 156.6,
              "median_bpm": 156,
              "sample_count": 65
            }
          }
        }
      },
      "gap_days_discipline": 1,
      "pace": {
        "distance_weighted_sec_per_km": 326.94,
        "median_sec_per_km": 338.36,
        "sample_count": 15
      }
    },
    "bike": {
      "units": {
        "volume": "hours",
        "session_distance": "km",
        "session_duration": "min",
        "long_session": "hours",
        "elevation_gain": "m"
      },
      "weekly": {
        "sessions_median": 3,
        "volume_median": 7.35,
        "volume_iqr": [
          6.56,
          8.77
        ],
        "zero_weeks": 0,
        "volume_cv": 0.488,
        "weeks_tracked": 9,
        "elevation_gain_median": 3094.28,
        "distance_km_median": 201.7221,
        "distance_km_iqr": [
          190.4026,
          239.2939
        ]
      },
      "session": {
        "distance_median": 57.97,
        "duration_median_min": 144.1,
        "sessions_tracked": 27,
        "elevation_gain_median_m": 743.48
      },
      "long_session": {
        "weekly_max_median": 3.46
      },
      "intensity": {
        "speed": {
          "distance_weighted_kmh": 26.04,
          "median_kmh": 26.17,
          "sample_count": 27
        },
        "power": {
          "duration_weighted_watts": 168.1,
          "median_watts": 175.76,
          "sample_count": 27
        },
        "power_wkg": {
          "duration_weighted_wkg": 2.1,
          "median_wkg": 2.2,
          "sample_count": 27
        },
        "heart_rate": {
          "duration_weighted_bpm": 30.5,
          "median_bpm": 30.64,
          "sample_count": 0
        }
      },
      "coverage": {
        "total_activities": 27,
        "pace_or_speed_coverage_fraction": 1,
        "hr_fraction": 0,
        "power_fraction": 1,
        "device_watts_fraction": 0.19
      },
      "confidence": "medium",
      "history": {
        "gap_days": 1,
        "recent": {
          "weekly": {
            "sessions_median": 3,
            "volume_median": 7.880833333333333,
            "volume_iqr": [
              7.388888888888889,
              9.179722222222221
            ],
            "zero_weeks": 0,
            "volume_cv": 0.488,
            "weeks_tracked": 9,
            "elevation_gain_median": 3478,
            "distance_km_median": 201.7221,
            "distance_km_iqr": [
              190.4026,
              239.2939
            ]
          },
          "session": {
            "distance_median": 67.7188,
            "duration_median_min": 167.81666666666666,
            "sessions_tracked": 27,
            "elevation_gain_median_m": 873
          },
          "long_session": {
            "weekly_max_median": 3.7544444444444443
          },
          "intensity": {
            "speed": {
              "distance_weighted_kmh": 26.46,
              "median_kmh": 26.84,
              "sample_count": 27
            },
            "power": {
              "duration_weighted_watts": 172.7,
              "median_watts": 183.1,
              "sample_count": 27
            },
            "power_wkg": {
              "duration_weighted_wkg": 2.159,
              "median_wkg": 2.289,
              "sample_count": 27
            },
            "heart_rate": {
              "duration_weighted_bpm": 0,
              "median_bpm": 0,
              "sample_count": 0
            }
          }
        },
        "historical": {
          "weekly": {
            "sessions_median": 3,
            "volume_median": 5.2027777777777775,
            "volume_iqr": [
              3.2675,
              7.1075
            ],
            "zero_weeks": 4,
            "volume_cv": 0.537,
            "weeks_tracked": 97,
            "elevation_gain_median": 1559.4,
            "distance_km_median": 120.8281,
            "distance_km_iqr": [
              60.653499999999994,
              167.50060000000002
            ]
          },
          "session": {
            "distance_median": 18.9821,
            "duration_median_min": 49.233333333333334,
            "sessions_tracked": 345,
            "elevation_gain_median_m": 225.4
          },
          "long_session": {
            "weekly_max_median": 2.2625
          },
          "intensity": {
            "speed": {
              "distance_weighted_kmh": 24.38,
              "median_kmh": 23.5,
              "sample_count": 330
            },
            "power": {
              "duration_weighted_watts": 149.7,
              "median_watts": 146.4,
              "sample_count": 290
            },
            "power_wkg": {
              "duration_weighted_wkg": 1.872,
              "median_wkg": 1.83,
              "sample_count": 290
            },
            "heart_rate": {
              "duration_weighted_bpm": 152.5,
              "median_bpm": 153.2,
              "sample_count": 294
            }
          }
        }
      },
      "gap_days_discipline": 1,
      "speed": {
        "distance_weighted_kmh": 26.46,
        "median_kmh": 26.84,
        "sample_count": 27
      },
      "power": {
        "duration_weighted_watts": 172.7,
        "median_watts": 183.1,
        "sample_count": 27
      },
      "power_wkg": {
        "duration_weighted_wkg": 2.1,
        "median_wkg": 2.2,
        "sample_count": 27
      }
    },
    "swim": {
      "units": {
        "volume": "km",
        "session_distance": "km",
        "session_duration": "min",
        "long_session": "km"
      },
      "weekly": {
        "sessions_median": 0,
        "volume_median": 0,
        "volume_iqr": [
          0,
          0.51
        ],
        "zero_weeks": 8,
        "volume_cv": 2.828,
        "weeks_tracked": 9,
        "elevation_gain_median": 0,
        "distance_km_median": 0,
        "distance_km_iqr": [
          0,
          0
        ]
      },
      "session": {
        "distance_median": 1.65,
        "duration_median_min": 32.26,
        "sessions_tracked": 1,
        "elevation_gain_median_m": 0
      },
      "long_session": {
        "weekly_max_median": 0
      },
      "intensity": {},
      "coverage": {
        "total_activities": 1,
        "pace_or_speed_coverage_fraction": 1,
        "hr_fraction": 0
      },
      "confidence": "low",
      "history": {
        "gap_days": 47,
        "recent": {
          "weekly": {
            "sessions_median": 0,
            "volume_median": 0,
            "volume_iqr": [
              0,
              0
            ],
            "zero_weeks": 8,
            "volume_cv": 2.828,
            "weeks_tracked": 9,
            "elevation_gain_median": 0,
            "distance_km_median": 0,
            "distance_km_iqr": [
              0,
              0
            ]
          },
          "session": {
            "distance_median": 1.5008,
            "duration_median_min": 29.083333333333332,
            "sessions_tracked": 1,
            "elevation_gain_median_m": 0
          },
          "long_session": {
            "weekly_max_median": 0
          },
          "intensity": {}
        },
        "historical": {
          "weekly": {
            "sessions_median": 0,
            "volume_median": 0,
            "volume_iqr": [
              0,
              1.7
            ],
            "zero_weeks": 66,
            "volume_cv": 1.803,
            "weeks_tracked": 97,
            "elevation_gain_median": 0,
            "distance_km_median": 0,
            "distance_km_iqr": [
              0,
              0
            ]
          },
          "session": {
            "distance_median": 2,
            "duration_median_min": 39.65833333333333,
            "sessions_tracked": 58,
            "elevation_gain_median_m": 0
          },
          "long_session": {
            "weekly_max_median": 0
          },
          "intensity": {}
        }
      },
      "gap_days_discipline": 47,
      "pace": {
        "distance_weighted_sec_per_100m": 132.83,
        "median_sec_per_100m": 129.15,
        "sample_count": 56
      }
    }
  },
  "context": {
    "short_window": {
      "start": "2026-01-21",
      "end": "2026-02-03",
      "activity_count": 13
    },
    "long_window": {
      "start": "2025-10-15",
      "end": "2026-02-03",
      "activity_count": 96
    }
  },
  "composite": {
    "weekly": {
      "total_endurance_hours_median": 8.85,
      "total_endurance_hours_iqr": [
        7.522500000000001,
        9.62
      ],
      "total_endurance_hours_cv": 0.466,
      "total_sessions_median": 5,
      "total_sessions_iqr": [
        3,
        7
      ],
      "total_sessions_cv": 0.379,
      "aerobic_points_median": 9.13,
      "aerobic_points_iqr": [
        8.000600283905484,
        10.807629282706323
      ],
      "aerobic_points_cv": 0.422
    },
    "by_sport": {
      "weekly_aerobic_points_median": {
        "run": 0.85,
        "bike": 8.03,
        "swim": 0
      }
    },
    "impact": {
      "weekly_run_km_median": 8,
      "weekly_run_hours_median": 0.67,
      "run_time_share_median": 0.078
    },
    "flags": {
      "high_cardio_low_impact": true
    }
  },
  "restart": {
    "gap_days_any": 1,
    "reentry_level": 0,
    "week1": {
      "run": {
        "volume_cap": 5.44,
        "long_cap": 3.57
      },
      "bike": {
        "volume_cap": 7.35,
        "long_cap": 3.46
      },
      "swim": {
        "volume_cap": 0,
        "long_cap": 0
      }
    },
    "week2": {
      "run": {
        "volume_cap": 6.4,
        "long_cap": 4.11
      },
      "bike": {
        "volume_cap": 7.35,
        "long_cap": 3.46
      },
      "swim": {
        "volume_cap": 0,
        "long_cap": 0
      }
    }
  },
  "transfer": {
    "run_easy_pace_sec_per_km_range": [
      355.3,
      423
    ],
    "run_easy_pace_reason": null,
    "run_intro_weekly_time_min_range": [
      45,
      90
    ],
    "transfer_confidence": "low"
  }
}
